{
    "endpoints": [
        {
            "name": "menu",
            "alwaysPresent": true,
            "endpoint": "http://localhost:4202/main.js",
            "menu": {
                "materialicon": "360",
                "label": "360",
                "route": "/360",
                "isClicked": false
            }
        },
        {
            "name": "utente",
            "alwaysPresent": false,
            "endpoint": "http://localhost:4201/main.js",
            "menu": {
                "materialicon": "home",
                "label": "UTENTE",
                "route": "/utente",
                "isClicked": false
            },
            "parcels": [
                "parcel",
                "utente"
            ]
        },
        {
            "name": "parcel",
            "alwaysPresent": false,
            "endpoint": "http://localhost:4203/main.js"
        }
    ]
}